random_data_gen/__init__.py
random_data_gen/data_generator.py
random_data_gen/features/transactional_features.py
random_data_gen-0.1.3.dist-info/WHEEL
random_data_gen-0.1.3.dist-info/METADATA
random_data_gen-0.1.3.dist-info/RECORD
