Metadata-Version: 2.1
Name: random-data-gen
Version: 0.1.3
Summary: Package to generate random transactional data
Home-page: https://github.com/felipesassi/random-data-gen
Author: Felipe Sassi
Author-email: felipesassi@outlook.com
Requires-Python: >=3.8,<4.0
Classifier: Programming Language :: Python :: 3
Classifier: Programming Language :: Python :: 3.10
Classifier: Programming Language :: Python :: 3.8
Classifier: Programming Language :: Python :: 3.9
Requires-Dist: numpy (>=1.22.1,<2.0.0)
Requires-Dist: pandas (>=1.4.0,<2.0.0)
Project-URL: Repository, https://github.com/felipesassi/random-data-gen
